smssdk/__init__.py
smssdk/https/__init__.py
smssdk/https/auth/__init__.py
smssdk/https/auth/auth.py
smssdk/https/requests/__init__.py
smssdk/https/requests/abstract_func.py
smssdk/https/requests/api_request.py
smssdk/tcp/__init__.py
smssdk/tcp/cmpp/__init__.py
smssdk/tcp/cmpp/callback/__init__.py
smssdk/tcp/cmpp/reqdata/__init__.py
smssdk/tcp/cmpp/reqdata/connect_req.py
smssdk/tcp/cmpp/reqdata/submit_req.py
smssdk/tcp/cmpp/reqdata/terminate_req.py
smssdk/tcp/cmpp/resdata/__init__.py
smssdk/tcp/cmpp/resdata/active_req.py
smssdk/tcp/cmpp/resdata/connect_res.py
smssdk/tcp/cmpp/resdata/deliver_req.py
smssdk/tcp/cmpp/resdata/submit_res.py
smssdk/tcp/cmpp/resdata/terminate_res.py
smssdk/tcp/cmpp/resdata/router/__init__.py
smssdk/tcp/cmpp/sockettool/__init__.py
smssdk/utils/__init__.py
smssdk/utils/exceptions.py
smssdk/utils/logger.py
smssdk/utils/mythread.py
smssdk/utils/values.py
sms_sdk-0.0.3.dist-info/LICENSE.txt
sms_sdk-0.0.3.dist-info/METADATA
sms_sdk-0.0.3.dist-info/WHEEL
sms_sdk-0.0.3.dist-info/top_level.txt
sms_sdk-0.0.3.dist-info/RECORD
