Metadata-Version: 2.1
Name: sms-sdk
Version: 0.0.3
Summary: sms sdk
Home-page: UNKNOWN
Author: zgl
Author-email: 
License: MIT
Keywords: sms sdk
Platform: UNKNOWN
License-File: LICENSE.txt
Requires-Dist: colorama (~=0.4.4)
Requires-Dist: requests (~=2.28.1)
Requires-Dist: zpystream (~=0.1.1)
